eipiphany_time/__init__.py
eipiphany_time/component/__init__.py
eipiphany_time/component/time_interval_configuration.py
eipiphany_time/component/time_interval_endpoint.py
eipiphany_time/component/time_interval_source.py
eipiphany_time-0.1.0.dev20230306154257.dist-info/METADATA
eipiphany_time-0.1.0.dev20230306154257.dist-info/WHEEL
eipiphany_time-0.1.0.dev20230306154257.dist-info/top_level.txt
eipiphany_time-0.1.0.dev20230306154257.dist-info/RECORD
