Metadata-Version: 2.1
Name: eipiphany-time
Version: 0.1.0.dev20230306154257
Summary: Simple Multiprocessing EIP Framework For Python: Time Components
Home-page: https://github.com/ci-cmg/eipiphany
Classifier: Programming Language :: Python :: 3
Classifier: License :: OSI Approved :: MIT License
Classifier: Operating System :: OS Independent
Requires-Python: >=3.9
Requires-Dist: eipiphany-core (==0.1.0.dev20230306154257)
